<?xml version="1.0" encoding="UTF-8"?>
<!DOCTYPE header PUBLIC "-//Apple Computer//DTD HEADERDOC 1.6//EN" "/System/Library/DTDs/HeaderDoc-1.6.dtd">
<header id="//xsdoc_ref/doc/header/SKTypes.h" lang="c" filename="SKTypes.h" headerpath="/Users/macmade/Documents/Macmade/GitHub/ShellKit/Documentation/../ShellKit/Classes/ShellKit/SKTypes.h"><name>SKTypes.h</name>
<includes>
<include><hd_link logicalPath="//xsdoc_ref/doc/header/Foundation.h">&lt;Foundation/Foundation.h&gt;</hd_link></include>
</includes>
<desc><p/></desc>
<typedefs><typedef id="//xsdoc_ref/c/tdef/NS_ENUM" lang="c" type="funcPtr"><name>NS_ENUM</name>
<abstract><p>Defines status icons
</p></abstract>
<parameterlist>
<parameter><name>SKStatusNone</name><desc><p>No status</p></desc></parameter>
<parameter><name>SKStatusSuccess</name><desc><p>Sucess status icon</p></desc></parameter>
<parameter><name>SKStatusFatal</name><desc><p>Fatal error status icon</p></desc></parameter>
<parameter><name>SKStatusError</name><desc><p>Error status icon</p></desc></parameter>
<parameter><name>SKStatusWarning</name><desc><p>Warning status icon</p></desc></parameter>
<parameter><name>SKStatusInfo</name><desc><p>Info status icon</p></desc></parameter>
<parameter><name>SKStatusDebug</name><desc><p>Debug status icon</p></desc></parameter>
<parameter><name>SKStatusBuild</name><desc><p>Build status icon</p></desc></parameter>
<parameter><name>SKStatusInstall</name><desc><p>Install status icon</p></desc></parameter>
<parameter><name>SKStatusIdea</name><desc><p>Idea status icon</p></desc></parameter>
<parameter><name>SKStatusSettings</name><desc><p>Settings status icon</p></desc></parameter>
<parameter><name>SKStatusSecurity</name><desc><p>Security status icon</p></desc></parameter>
<parameter><name>SKStatusExecute</name><desc><p>Executing status icon</p></desc></parameter>
<parameter><name>SKStatusSearch</name><desc><p>Search status icon</p></desc></parameter>
<parameter><name>SKStatusTarget</name><desc><p>Target status icon</p></desc></parameter>
<parameter><name>SKStatusComment</name><desc><p>Comment status icon</p></desc></parameter>
<parameter><name>SKStatusFile</name><desc><p>File status icon</p></desc></parameter>
<parameter><name>SKStatusFolder</name><desc><p>Folder status icon</p></desc></parameter>
<parameter><name>SKStatusTrash</name><desc><p>Trash status icon</p></desc></parameter>
<parameter><name>SKStatusLink</name><desc><p>Link status icon</p></desc></parameter>
<parameter><name>SKStatusMail</name><desc><p>Mail message status icon</p></desc></parameter>
<parameter><name>SKStatusAttachement</name><desc><p>Message attachmnet status icon</p></desc></parameter>
<parameter><name>SKStatusEdit</name><desc><p>Edit status icon</p></desc></parameter>
<parameter><name>SKStatusPin</name><desc><p>Push pin status icon</p></desc></parameter>
<parameter><name>SKStatusLock</name><desc><p>Lock status icon</p></desc></parameter>
<parameter><name>SKStatusRocket</name><desc><p>Rocket status icon</p></desc></parameter>
<parameter><name>SKStatusFire</name><desc><p>Fire status icon</p></desc></parameter>
<parameter><name>SKStatusLightning</name><desc><p>Lightning status icon</p></desc></parameter>
<parameter><name>SKStatusBug</name><desc><p>Bug status icon</p></desc></parameter>
</parameterlist>
<parsedparameterlist>
<parsedparameter><type></type><name>NSInteger</name></parsedparameter>
<parsedparameter><type></type><name>SKStatus</name></parsedparameter>
<parsedparameter><type>SKStatusNone,
                 SKStatusSuccess,
              SKStatusFatal,
                SKStatusError,
                SKStatusWarning,
              SKStatusInfo,
                 SKStatusDebug,
                SKStatusBuild,
                SKStatusInstall,
              SKStatusIdea,
                 SKStatusSettings,
             SKStatusSecurity,
             SKStatusExecute,
              SKStatusSearch,
               SKStatusTarget,
               SKStatusComment,
              SKStatusFile,
                 SKStatusFolder,
               SKStatusTrash,
                SKStatusLink,
                 SKStatusMail,
                 SKStatusAttachement,
          SKStatusEdit,
                 SKStatusPin,
                  SKStatusLock,
                 SKStatusRocket,
               SKStatusFire,
                 SKStatusLightning,
             SKStatusBug</type><name>SKStatusLink</name></parsedparameter>
<parsedparameter><type>SKStatusNone,
                 SKStatusSuccess,
              SKStatusFatal,
                SKStatusError,
                SKStatusWarning,
              SKStatusInfo,
                 SKStatusDebug,
                SKStatusBuild,
                SKStatusInstall,
              SKStatusIdea,
                 SKStatusSettings,
             SKStatusSecurity,
             SKStatusExecute,
              SKStatusSearch,
               SKStatusTarget,
               SKStatusComment,
              SKStatusFile,
                 SKStatusFolder,
               SKStatusTrash,
                SKStatusLink,
                 SKStatusMail,
                 SKStatusAttachement,
          SKStatusEdit,
                 SKStatusPin,
                  SKStatusLock,
                 SKStatusRocket,
               SKStatusFire,
                 SKStatusLightning,
             SKStatusBug</type><name>SKStatusLock</name></parsedparameter>
<parsedparameter><type>SKStatusNone,
                 SKStatusSuccess,
              SKStatusFatal,
                SKStatusError,
                SKStatusWarning,
              SKStatusInfo,
                 SKStatusDebug,
                SKStatusBuild,
                SKStatusInstall,
              SKStatusIdea,
                 SKStatusSettings,
             SKStatusSecurity,
             SKStatusExecute,
              SKStatusSearch,
               SKStatusTarget,
               SKStatusComment,
              SKStatusFile,
                 SKStatusFolder,
               SKStatusTrash,
                SKStatusLink,
                 SKStatusMail,
                 SKStatusAttachement,
          SKStatusEdit,
                 SKStatusPin,
                  SKStatusLock,
                 SKStatusRocket,
               SKStatusFire,
                 SKStatusLightning,
             SKStatusBug</type><name>SKStatusFire</name></parsedparameter>
<parsedparameter><type>SKStatusNone,
                 SKStatusSuccess,
              SKStatusFatal,
                SKStatusError,
                SKStatusWarning,
              SKStatusInfo,
                 SKStatusDebug,
                SKStatusBuild,
                SKStatusInstall,
              SKStatusIdea,
                 SKStatusSettings,
             SKStatusSecurity,
             SKStatusExecute,
              SKStatusSearch,
               SKStatusTarget,
               SKStatusComment,
              SKStatusFile,
                 SKStatusFolder,
               SKStatusTrash,
                SKStatusLink,
                 SKStatusMail,
                 SKStatusAttachement,
          SKStatusEdit,
                 SKStatusPin,
                  SKStatusLock,
                 SKStatusRocket,
               SKStatusFire,
                 SKStatusLightning,
             SKStatusBug</type><name>SKStatusAttachement</name></parsedparameter>
<parsedparameter><type>SKStatusNone,
                 SKStatusSuccess,
              SKStatusFatal,
                SKStatusError,
                SKStatusWarning,
              SKStatusInfo,
                 SKStatusDebug,
                SKStatusBuild,
                SKStatusInstall,
              SKStatusIdea,
                 SKStatusSettings,
             SKStatusSecurity,
             SKStatusExecute,
              SKStatusSearch,
               SKStatusTarget,
               SKStatusComment,
              SKStatusFile,
                 SKStatusFolder,
               SKStatusTrash,
                SKStatusLink,
                 SKStatusMail,
                 SKStatusAttachement,
          SKStatusEdit,
                 SKStatusPin,
                  SKStatusLock,
                 SKStatusRocket,
               SKStatusFire,
                 SKStatusLightning,
             SKStatusBug</type><name>SKStatusSettings</name></parsedparameter>
<parsedparameter><type>SKStatusNone,
                 SKStatusSuccess,
              SKStatusFatal,
                SKStatusError,
                SKStatusWarning,
              SKStatusInfo,
                 SKStatusDebug,
                SKStatusBuild,
                SKStatusInstall,
              SKStatusIdea,
                 SKStatusSettings,
             SKStatusSecurity,
             SKStatusExecute,
              SKStatusSearch,
               SKStatusTarget,
               SKStatusComment,
              SKStatusFile,
                 SKStatusFolder,
               SKStatusTrash,
                SKStatusLink,
                 SKStatusMail,
                 SKStatusAttachement,
          SKStatusEdit,
                 SKStatusPin,
                  SKStatusLock,
                 SKStatusRocket,
               SKStatusFire,
                 SKStatusLightning,
             SKStatusBug</type><name>SKStatusNone</name></parsedparameter>
<parsedparameter><type>SKStatusNone,
                 SKStatusSuccess,
              SKStatusFatal,
                SKStatusError,
                SKStatusWarning,
              SKStatusInfo,
                 SKStatusDebug,
                SKStatusBuild,
                SKStatusInstall,
              SKStatusIdea,
                 SKStatusSettings,
             SKStatusSecurity,
             SKStatusExecute,
              SKStatusSearch,
               SKStatusTarget,
               SKStatusComment,
              SKStatusFile,
                 SKStatusFolder,
               SKStatusTrash,
                SKStatusLink,
                 SKStatusMail,
                 SKStatusAttachement,
          SKStatusEdit,
                 SKStatusPin,
                  SKStatusLock,
                 SKStatusRocket,
               SKStatusFire,
                 SKStatusLightning,
             SKStatusBug</type><name>SKStatusWarning</name></parsedparameter>
<parsedparameter><type>SKStatusNone,
                 SKStatusSuccess,
              SKStatusFatal,
                SKStatusError,
                SKStatusWarning,
              SKStatusInfo,
                 SKStatusDebug,
                SKStatusBuild,
                SKStatusInstall,
              SKStatusIdea,
                 SKStatusSettings,
             SKStatusSecurity,
             SKStatusExecute,
              SKStatusSearch,
               SKStatusTarget,
               SKStatusComment,
              SKStatusFile,
                 SKStatusFolder,
               SKStatusTrash,
                SKStatusLink,
                 SKStatusMail,
                 SKStatusAttachement,
          SKStatusEdit,
                 SKStatusPin,
                  SKStatusLock,
                 SKStatusRocket,
               SKStatusFire,
                 SKStatusLightning,
             SKStatusBug</type><name>SKStatusPin</name></parsedparameter>
<parsedparameter><type>SKStatusNone,
                 SKStatusSuccess,
              SKStatusFatal,
                SKStatusError,
                SKStatusWarning,
              SKStatusInfo,
                 SKStatusDebug,
                SKStatusBuild,
                SKStatusInstall,
              SKStatusIdea,
                 SKStatusSettings,
             SKStatusSecurity,
             SKStatusExecute,
              SKStatusSearch,
               SKStatusTarget,
               SKStatusComment,
              SKStatusFile,
                 SKStatusFolder,
               SKStatusTrash,
                SKStatusLink,
                 SKStatusMail,
                 SKStatusAttachement,
          SKStatusEdit,
                 SKStatusPin,
                  SKStatusLock,
                 SKStatusRocket,
               SKStatusFire,
                 SKStatusLightning,
             SKStatusBug</type><name>SKStatusInfo</name></parsedparameter>
<parsedparameter><type>SKStatusNone,
                 SKStatusSuccess,
              SKStatusFatal,
                SKStatusError,
                SKStatusWarning,
              SKStatusInfo,
                 SKStatusDebug,
                SKStatusBuild,
                SKStatusInstall,
              SKStatusIdea,
                 SKStatusSettings,
             SKStatusSecurity,
             SKStatusExecute,
              SKStatusSearch,
               SKStatusTarget,
               SKStatusComment,
              SKStatusFile,
                 SKStatusFolder,
               SKStatusTrash,
                SKStatusLink,
                 SKStatusMail,
                 SKStatusAttachement,
          SKStatusEdit,
                 SKStatusPin,
                  SKStatusLock,
                 SKStatusRocket,
               SKStatusFire,
                 SKStatusLightning,
             SKStatusBug</type><name>SKStatusTarget</name></parsedparameter>
<parsedparameter><type>SKStatusNone,
                 SKStatusSuccess,
              SKStatusFatal,
                SKStatusError,
                SKStatusWarning,
              SKStatusInfo,
                 SKStatusDebug,
                SKStatusBuild,
                SKStatusInstall,
              SKStatusIdea,
                 SKStatusSettings,
             SKStatusSecurity,
             SKStatusExecute,
              SKStatusSearch,
               SKStatusTarget,
               SKStatusComment,
              SKStatusFile,
                 SKStatusFolder,
               SKStatusTrash,
                SKStatusLink,
                 SKStatusMail,
                 SKStatusAttachement,
          SKStatusEdit,
                 SKStatusPin,
                  SKStatusLock,
                 SKStatusRocket,
               SKStatusFire,
                 SKStatusLightning,
             SKStatusBug</type><name>SKStatusSuccess</name></parsedparameter>
<parsedparameter><type>SKStatusNone,
                 SKStatusSuccess,
              SKStatusFatal,
                SKStatusError,
                SKStatusWarning,
              SKStatusInfo,
                 SKStatusDebug,
                SKStatusBuild,
                SKStatusInstall,
              SKStatusIdea,
                 SKStatusSettings,
             SKStatusSecurity,
             SKStatusExecute,
              SKStatusSearch,
               SKStatusTarget,
               SKStatusComment,
              SKStatusFile,
                 SKStatusFolder,
               SKStatusTrash,
                SKStatusLink,
                 SKStatusMail,
                 SKStatusAttachement,
          SKStatusEdit,
                 SKStatusPin,
                  SKStatusLock,
                 SKStatusRocket,
               SKStatusFire,
                 SKStatusLightning,
             SKStatusBug</type><name>SKStatusFile</name></parsedparameter>
<parsedparameter><type>SKStatusNone,
                 SKStatusSuccess,
              SKStatusFatal,
                SKStatusError,
                SKStatusWarning,
              SKStatusInfo,
                 SKStatusDebug,
                SKStatusBuild,
                SKStatusInstall,
              SKStatusIdea,
                 SKStatusSettings,
             SKStatusSecurity,
             SKStatusExecute,
              SKStatusSearch,
               SKStatusTarget,
               SKStatusComment,
              SKStatusFile,
                 SKStatusFolder,
               SKStatusTrash,
                SKStatusLink,
                 SKStatusMail,
                 SKStatusAttachement,
          SKStatusEdit,
                 SKStatusPin,
                  SKStatusLock,
                 SKStatusRocket,
               SKStatusFire,
                 SKStatusLightning,
             SKStatusBug</type><name>SKStatusExecute</name></parsedparameter>
<parsedparameter><type>SKStatusNone,
                 SKStatusSuccess,
              SKStatusFatal,
                SKStatusError,
                SKStatusWarning,
              SKStatusInfo,
                 SKStatusDebug,
                SKStatusBuild,
                SKStatusInstall,
              SKStatusIdea,
                 SKStatusSettings,
             SKStatusSecurity,
             SKStatusExecute,
              SKStatusSearch,
               SKStatusTarget,
               SKStatusComment,
              SKStatusFile,
                 SKStatusFolder,
               SKStatusTrash,
                SKStatusLink,
                 SKStatusMail,
                 SKStatusAttachement,
          SKStatusEdit,
                 SKStatusPin,
                  SKStatusLock,
                 SKStatusRocket,
               SKStatusFire,
                 SKStatusLightning,
             SKStatusBug</type><name>SKStatusMail</name></parsedparameter>
<parsedparameter><type>SKStatusNone,
                 SKStatusSuccess,
              SKStatusFatal,
                SKStatusError,
                SKStatusWarning,
              SKStatusInfo,
                 SKStatusDebug,
                SKStatusBuild,
                SKStatusInstall,
              SKStatusIdea,
                 SKStatusSettings,
             SKStatusSecurity,
             SKStatusExecute,
              SKStatusSearch,
               SKStatusTarget,
               SKStatusComment,
              SKStatusFile,
                 SKStatusFolder,
               SKStatusTrash,
                SKStatusLink,
                 SKStatusMail,
                 SKStatusAttachement,
          SKStatusEdit,
                 SKStatusPin,
                  SKStatusLock,
                 SKStatusRocket,
               SKStatusFire,
                 SKStatusLightning,
             SKStatusBug</type><name>SKStatusIdea</name></parsedparameter>
<parsedparameter><type>SKStatusNone,
                 SKStatusSuccess,
              SKStatusFatal,
                SKStatusError,
                SKStatusWarning,
              SKStatusInfo,
                 SKStatusDebug,
                SKStatusBuild,
                SKStatusInstall,
              SKStatusIdea,
                 SKStatusSettings,
             SKStatusSecurity,
             SKStatusExecute,
              SKStatusSearch,
               SKStatusTarget,
               SKStatusComment,
              SKStatusFile,
                 SKStatusFolder,
               SKStatusTrash,
                SKStatusLink,
                 SKStatusMail,
                 SKStatusAttachement,
          SKStatusEdit,
                 SKStatusPin,
                  SKStatusLock,
                 SKStatusRocket,
               SKStatusFire,
                 SKStatusLightning,
             SKStatusBug</type><name>SKStatusInstall</name></parsedparameter>
<parsedparameter><type>SKStatusNone,
                 SKStatusSuccess,
              SKStatusFatal,
                SKStatusError,
                SKStatusWarning,
              SKStatusInfo,
                 SKStatusDebug,
                SKStatusBuild,
                SKStatusInstall,
              SKStatusIdea,
                 SKStatusSettings,
             SKStatusSecurity,
             SKStatusExecute,
              SKStatusSearch,
               SKStatusTarget,
               SKStatusComment,
              SKStatusFile,
                 SKStatusFolder,
               SKStatusTrash,
                SKStatusLink,
                 SKStatusMail,
                 SKStatusAttachement,
          SKStatusEdit,
                 SKStatusPin,
                  SKStatusLock,
                 SKStatusRocket,
               SKStatusFire,
                 SKStatusLightning,
             SKStatusBug</type><name>SKStatusLightning</name></parsedparameter>
<parsedparameter><type>SKStatusNone,
                 SKStatusSuccess,
              SKStatusFatal,
                SKStatusError,
                SKStatusWarning,
              SKStatusInfo,
                 SKStatusDebug,
                SKStatusBuild,
                SKStatusInstall,
              SKStatusIdea,
                 SKStatusSettings,
             SKStatusSecurity,
             SKStatusExecute,
              SKStatusSearch,
               SKStatusTarget,
               SKStatusComment,
              SKStatusFile,
                 SKStatusFolder,
               SKStatusTrash,
                SKStatusLink,
                 SKStatusMail,
                 SKStatusAttachement,
          SKStatusEdit,
                 SKStatusPin,
                  SKStatusLock,
                 SKStatusRocket,
               SKStatusFire,
                 SKStatusLightning,
             SKStatusBug</type><name>SKStatusTrash</name></parsedparameter>
<parsedparameter><type>SKStatusNone,
                 SKStatusSuccess,
              SKStatusFatal,
                SKStatusError,
                SKStatusWarning,
              SKStatusInfo,
                 SKStatusDebug,
                SKStatusBuild,
                SKStatusInstall,
              SKStatusIdea,
                 SKStatusSettings,
             SKStatusSecurity,
             SKStatusExecute,
              SKStatusSearch,
               SKStatusTarget,
               SKStatusComment,
              SKStatusFile,
                 SKStatusFolder,
               SKStatusTrash,
                SKStatusLink,
                 SKStatusMail,
                 SKStatusAttachement,
          SKStatusEdit,
                 SKStatusPin,
                  SKStatusLock,
                 SKStatusRocket,
               SKStatusFire,
                 SKStatusLightning,
             SKStatusBug</type><name>SKStatusComment</name></parsedparameter>
<parsedparameter><type>SKStatusNone,
                 SKStatusSuccess,
              SKStatusFatal,
                SKStatusError,
                SKStatusWarning,
              SKStatusInfo,
                 SKStatusDebug,
                SKStatusBuild,
                SKStatusInstall,
              SKStatusIdea,
                 SKStatusSettings,
             SKStatusSecurity,
             SKStatusExecute,
              SKStatusSearch,
               SKStatusTarget,
               SKStatusComment,
              SKStatusFile,
                 SKStatusFolder,
               SKStatusTrash,
                SKStatusLink,
                 SKStatusMail,
                 SKStatusAttachement,
          SKStatusEdit,
                 SKStatusPin,
                  SKStatusLock,
                 SKStatusRocket,
               SKStatusFire,
                 SKStatusLightning,
             SKStatusBug</type><name>SKStatusError</name></parsedparameter>
<parsedparameter><type>SKStatusNone,
                 SKStatusSuccess,
              SKStatusFatal,
                SKStatusError,
                SKStatusWarning,
              SKStatusInfo,
                 SKStatusDebug,
                SKStatusBuild,
                SKStatusInstall,
              SKStatusIdea,
                 SKStatusSettings,
             SKStatusSecurity,
             SKStatusExecute,
              SKStatusSearch,
               SKStatusTarget,
               SKStatusComment,
              SKStatusFile,
                 SKStatusFolder,
               SKStatusTrash,
                SKStatusLink,
                 SKStatusMail,
                 SKStatusAttachement,
          SKStatusEdit,
                 SKStatusPin,
                  SKStatusLock,
                 SKStatusRocket,
               SKStatusFire,
                 SKStatusLightning,
             SKStatusBug</type><name>SKStatusFatal</name></parsedparameter>
<parsedparameter><type>SKStatusNone,
                 SKStatusSuccess,
              SKStatusFatal,
                SKStatusError,
                SKStatusWarning,
              SKStatusInfo,
                 SKStatusDebug,
                SKStatusBuild,
                SKStatusInstall,
              SKStatusIdea,
                 SKStatusSettings,
             SKStatusSecurity,
             SKStatusExecute,
              SKStatusSearch,
               SKStatusTarget,
               SKStatusComment,
              SKStatusFile,
                 SKStatusFolder,
               SKStatusTrash,
                SKStatusLink,
                 SKStatusMail,
                 SKStatusAttachement,
          SKStatusEdit,
                 SKStatusPin,
                  SKStatusLock,
                 SKStatusRocket,
               SKStatusFire,
                 SKStatusLightning,
             SKStatusBug</type><name>SKStatusRocket</name></parsedparameter>
<parsedparameter><type>SKStatusNone,
                 SKStatusSuccess,
              SKStatusFatal,
                SKStatusError,
                SKStatusWarning,
              SKStatusInfo,
                 SKStatusDebug,
                SKStatusBuild,
                SKStatusInstall,
              SKStatusIdea,
                 SKStatusSettings,
             SKStatusSecurity,
             SKStatusExecute,
              SKStatusSearch,
               SKStatusTarget,
               SKStatusComment,
              SKStatusFile,
                 SKStatusFolder,
               SKStatusTrash,
                SKStatusLink,
                 SKStatusMail,
                 SKStatusAttachement,
          SKStatusEdit,
                 SKStatusPin,
                  SKStatusLock,
                 SKStatusRocket,
               SKStatusFire,
                 SKStatusLightning,
             SKStatusBug</type><name>SKStatusEdit</name></parsedparameter>
<parsedparameter><type>SKStatusNone,
                 SKStatusSuccess,
              SKStatusFatal,
                SKStatusError,
                SKStatusWarning,
              SKStatusInfo,
                 SKStatusDebug,
                SKStatusBuild,
                SKStatusInstall,
              SKStatusIdea,
                 SKStatusSettings,
             SKStatusSecurity,
             SKStatusExecute,
              SKStatusSearch,
               SKStatusTarget,
               SKStatusComment,
              SKStatusFile,
                 SKStatusFolder,
               SKStatusTrash,
                SKStatusLink,
                 SKStatusMail,
                 SKStatusAttachement,
          SKStatusEdit,
                 SKStatusPin,
                  SKStatusLock,
                 SKStatusRocket,
               SKStatusFire,
                 SKStatusLightning,
             SKStatusBug</type><name>SKStatusDebug</name></parsedparameter>
<parsedparameter><type>SKStatusNone,
                 SKStatusSuccess,
              SKStatusFatal,
                SKStatusError,
                SKStatusWarning,
              SKStatusInfo,
                 SKStatusDebug,
                SKStatusBuild,
                SKStatusInstall,
              SKStatusIdea,
                 SKStatusSettings,
             SKStatusSecurity,
             SKStatusExecute,
              SKStatusSearch,
               SKStatusTarget,
               SKStatusComment,
              SKStatusFile,
                 SKStatusFolder,
               SKStatusTrash,
                SKStatusLink,
                 SKStatusMail,
                 SKStatusAttachement,
          SKStatusEdit,
                 SKStatusPin,
                  SKStatusLock,
                 SKStatusRocket,
               SKStatusFire,
                 SKStatusLightning,
             SKStatusBug</type><name>SKStatusSecurity</name></parsedparameter>
<parsedparameter><type>SKStatusNone,
                 SKStatusSuccess,
              SKStatusFatal,
                SKStatusError,
                SKStatusWarning,
              SKStatusInfo,
                 SKStatusDebug,
                SKStatusBuild,
                SKStatusInstall,
              SKStatusIdea,
                 SKStatusSettings,
             SKStatusSecurity,
             SKStatusExecute,
              SKStatusSearch,
               SKStatusTarget,
               SKStatusComment,
              SKStatusFile,
                 SKStatusFolder,
               SKStatusTrash,
                SKStatusLink,
                 SKStatusMail,
                 SKStatusAttachement,
          SKStatusEdit,
                 SKStatusPin,
                  SKStatusLock,
                 SKStatusRocket,
               SKStatusFire,
                 SKStatusLightning,
             SKStatusBug</type><name>SKStatusBuild</name></parsedparameter>
<parsedparameter><type>SKStatusNone,
                 SKStatusSuccess,
              SKStatusFatal,
                SKStatusError,
                SKStatusWarning,
              SKStatusInfo,
                 SKStatusDebug,
                SKStatusBuild,
                SKStatusInstall,
              SKStatusIdea,
                 SKStatusSettings,
             SKStatusSecurity,
             SKStatusExecute,
              SKStatusSearch,
               SKStatusTarget,
               SKStatusComment,
              SKStatusFile,
                 SKStatusFolder,
               SKStatusTrash,
                SKStatusLink,
                 SKStatusMail,
                 SKStatusAttachement,
          SKStatusEdit,
                 SKStatusPin,
                  SKStatusLock,
                 SKStatusRocket,
               SKStatusFire,
                 SKStatusLightning,
             SKStatusBug</type><name>SKStatusFolder</name></parsedparameter>
<parsedparameter><type>SKStatusNone,
                 SKStatusSuccess,
              SKStatusFatal,
                SKStatusError,
                SKStatusWarning,
              SKStatusInfo,
                 SKStatusDebug,
                SKStatusBuild,
                SKStatusInstall,
              SKStatusIdea,
                 SKStatusSettings,
             SKStatusSecurity,
             SKStatusExecute,
              SKStatusSearch,
               SKStatusTarget,
               SKStatusComment,
              SKStatusFile,
                 SKStatusFolder,
               SKStatusTrash,
                SKStatusLink,
                 SKStatusMail,
                 SKStatusAttachement,
          SKStatusEdit,
                 SKStatusPin,
                  SKStatusLock,
                 SKStatusRocket,
               SKStatusFire,
                 SKStatusLightning,
             SKStatusBug</type><name>SKStatusSearch</name></parsedparameter>
<parsedparameter><type>SKStatusNone,
                 SKStatusSuccess,
              SKStatusFatal,
                SKStatusError,
                SKStatusWarning,
              SKStatusInfo,
                 SKStatusDebug,
                SKStatusBuild,
                SKStatusInstall,
              SKStatusIdea,
                 SKStatusSettings,
             SKStatusSecurity,
             SKStatusExecute,
              SKStatusSearch,
               SKStatusTarget,
               SKStatusComment,
              SKStatusFile,
                 SKStatusFolder,
               SKStatusTrash,
                SKStatusLink,
                 SKStatusMail,
                 SKStatusAttachement,
          SKStatusEdit,
                 SKStatusPin,
                  SKStatusLock,
                 SKStatusRocket,
               SKStatusFire,
                 SKStatusLightning,
             SKStatusBug</type><name>SKStatusBug</name></parsedparameter>
</parsedparameterlist>
<attributelists><listattribute><name>See Also</name><list>
<item><name>SKStatus</name><value><hd_link logicalPath="//xsdoc_ref/doc/title:tdef/SKStatus" isseealso="yes">SKStatus</hd_link></value></item></list></listattribute>
</attributelists>
<declaration><declaration_keyword>typedef</declaration_keyword> <declaration_function>NS_ENUM</declaration_function>( <declaration_var>NSInteger</declaration_var>, <declaration_var>SKStatus</declaration_var> ) { 
    <declaration_var>SKStatusNone</declaration_var>, <declaration_comment>/*! No status */</declaration_comment>
    <declaration_var>SKStatusSuccess</declaration_var>, <declaration_comment>/*! Sucess status icon */</declaration_comment>
    <declaration_var>SKStatusFatal</declaration_var>, <declaration_comment>/*! Fatal error status icon */</declaration_comment>
    <declaration_var>SKStatusError</declaration_var>, <declaration_comment>/*! Error status icon */</declaration_comment>
    <declaration_var>SKStatusWarning</declaration_var>, <declaration_comment>/*! Warning status icon */</declaration_comment>
    <declaration_var>SKStatusInfo</declaration_var>, <declaration_comment>/*! Info status icon */</declaration_comment>
    <declaration_var>SKStatusDebug</declaration_var>, <declaration_comment>/*! Debug status icon */</declaration_comment>
    <declaration_var>SKStatusBuild</declaration_var>, <declaration_comment>/*! Build status icon */</declaration_comment>
    <declaration_var>SKStatusInstall</declaration_var>, <declaration_comment>/*! Install status icon */</declaration_comment>
    <declaration_var>SKStatusIdea</declaration_var>, <declaration_comment>/*! Idea status icon */</declaration_comment>
    <declaration_var>SKStatusSettings</declaration_var>, <declaration_comment>/*! Settings status icon */</declaration_comment>
    <declaration_var>SKStatusSecurity</declaration_var>, <declaration_comment>/*! Security status icon */</declaration_comment>
    <declaration_var>SKStatusExecute</declaration_var>, <declaration_comment>/*! Executing status icon */</declaration_comment>
    <declaration_var>SKStatusSearch</declaration_var>, <declaration_comment>/*! Search status icon */</declaration_comment>
    <declaration_var>SKStatusTarget</declaration_var>, <declaration_comment>/*! Target status icon */</declaration_comment>
    <declaration_var>SKStatusComment</declaration_var>, <declaration_comment>/*! Comment status icon */</declaration_comment>
    <declaration_var>SKStatusFile</declaration_var>, <declaration_comment>/*! File status icon */</declaration_comment>
    <declaration_var>SKStatusFolder</declaration_var>, <declaration_comment>/*! Folder status icon */</declaration_comment>
    <declaration_var>SKStatusTrash</declaration_var>, <declaration_comment>/*! Trash status icon */</declaration_comment>
    <declaration_var>SKStatusLink</declaration_var>, <declaration_comment>/*! Link status icon */</declaration_comment>
    <declaration_var>SKStatusMail</declaration_var>, <declaration_comment>/*! Mail message status icon */</declaration_comment>
    <declaration_var>SKStatusAttachement</declaration_var>, <declaration_comment>/*! Message attachmnet status icon */</declaration_comment>
    <declaration_var>SKStatusEdit</declaration_var>, <declaration_comment>/*! Edit status icon */</declaration_comment>
    <declaration_var>SKStatusPin</declaration_var>, <declaration_comment>/*! Push pin status icon */</declaration_comment>
    <declaration_var>SKStatusLock</declaration_var>, <declaration_comment>/*! Lock status icon */</declaration_comment>
    <declaration_var>SKStatusRocket</declaration_var>, <declaration_comment>/*! Rocket status icon */</declaration_comment>
    <declaration_var>SKStatusFire</declaration_var>, <declaration_comment>/*! Fire status icon */</declaration_comment>
    <declaration_var>SKStatusLightning</declaration_var>, <declaration_comment>/*! Lightning status icon */</declaration_comment>
    <declaration_var>SKStatusBug</declaration_var> <declaration_comment>/*! Bug status icon */</declaration_comment>
};  </declaration>
<desc><p/></desc>
<autorelated>
<relateduid>//xsdoc_ref/doc/title:tdef/SKStatus</relateduid>
</autorelated>
</typedef><typedef id="//xsdoc_ref/c/tdef/NS_ENUM_DONTLINK_1" lang="c" type="funcPtr"><name>NS_ENUM</name>
<abstract><p>Shell color type
</p></abstract>
<parameterlist>
<parameter><name>SKColorNone</name><desc><p>No color (clear)</p></desc></parameter>
<parameter><name>SKColorBlack</name><desc><p>Black color</p></desc></parameter>
<parameter><name>SKColorRed</name><desc><p>Red color</p></desc></parameter>
<parameter><name>SKColorGreen</name><desc><p>Green color</p></desc></parameter>
<parameter><name>SKColorYellow</name><desc><p>Yellow color</p></desc></parameter>
<parameter><name>SKColorBlue</name><desc><p>Blue color</p></desc></parameter>
<parameter><name>SKColorPurple</name><desc><p>Purple color</p></desc></parameter>
<parameter><name>SKColorWhite</name><desc><p>White color</p></desc></parameter>
<parameter><name>SKColorCyan</name><desc><p>Cyan color</p></desc></parameter>
</parameterlist>
<parsedparameterlist>
<parsedparameter><type></type><name>NSInteger</name></parsedparameter>
<parsedparameter><type></type><name>SKColor</name></parsedparameter>
<parsedparameter><type>SKColorNone,
          SKColorBlack,
         SKColorRed,
           SKColorGreen,
         SKColorYellow,
        SKColorBlue,
          SKColorPurple,
        SKColorWhite,
          SKColorCyan</type><name>SKColorNone</name></parsedparameter>
<parsedparameter><type>SKColorNone,
          SKColorBlack,
         SKColorRed,
           SKColorGreen,
         SKColorYellow,
        SKColorBlue,
          SKColorPurple,
        SKColorWhite,
          SKColorCyan</type><name>SKColorWhite</name></parsedparameter>
<parsedparameter><type>SKColorNone,
          SKColorBlack,
         SKColorRed,
           SKColorGreen,
         SKColorYellow,
        SKColorBlue,
          SKColorPurple,
        SKColorWhite,
          SKColorCyan</type><name>SKColorBlue</name></parsedparameter>
<parsedparameter><type>SKColorNone,
          SKColorBlack,
         SKColorRed,
           SKColorGreen,
         SKColorYellow,
        SKColorBlue,
          SKColorPurple,
        SKColorWhite,
          SKColorCyan</type><name>SKColorRed</name></parsedparameter>
<parsedparameter><type>SKColorNone,
          SKColorBlack,
         SKColorRed,
           SKColorGreen,
         SKColorYellow,
        SKColorBlue,
          SKColorPurple,
        SKColorWhite,
          SKColorCyan</type><name>SKColorYellow</name></parsedparameter>
<parsedparameter><type>SKColorNone,
          SKColorBlack,
         SKColorRed,
           SKColorGreen,
         SKColorYellow,
        SKColorBlue,
          SKColorPurple,
        SKColorWhite,
          SKColorCyan</type><name>SKColorBlack</name></parsedparameter>
<parsedparameter><type>SKColorNone,
          SKColorBlack,
         SKColorRed,
           SKColorGreen,
         SKColorYellow,
        SKColorBlue,
          SKColorPurple,
        SKColorWhite,
          SKColorCyan</type><name>SKColorGreen</name></parsedparameter>
<parsedparameter><type>SKColorNone,
          SKColorBlack,
         SKColorRed,
           SKColorGreen,
         SKColorYellow,
        SKColorBlue,
          SKColorPurple,
        SKColorWhite,
          SKColorCyan</type><name>SKColorPurple</name></parsedparameter>
<parsedparameter><type>SKColorNone,
          SKColorBlack,
         SKColorRed,
           SKColorGreen,
         SKColorYellow,
        SKColorBlue,
          SKColorPurple,
        SKColorWhite,
          SKColorCyan</type><name>SKColorCyan</name></parsedparameter>
</parsedparameterlist>
<attributelists><listattribute><name>See Also</name><list>
<item><name>SKColor</name><value><hd_link logicalPath="//xsdoc_ref/doc/title:tdef/SKColor" isseealso="yes">SKColor</hd_link></value></item></list></listattribute>
</attributelists>
<declaration><declaration_keyword>typedef</declaration_keyword> <declaration_function>NS_ENUM</declaration_function>( <declaration_var>NSInteger</declaration_var>, <declaration_var>SKColor</declaration_var> ) { 
    <declaration_var>SKColorNone</declaration_var>, <declaration_comment>/*! No color (clear) */</declaration_comment>
    <declaration_var>SKColorBlack</declaration_var>, <declaration_comment>/*! Black color */</declaration_comment>
    <declaration_var>SKColorRed</declaration_var>, <declaration_comment>/*! Red color */</declaration_comment>
    <declaration_var>SKColorGreen</declaration_var>, <declaration_comment>/*! Green color */</declaration_comment>
    <declaration_var>SKColorYellow</declaration_var>, <declaration_comment>/*! Yellow color */</declaration_comment>
    <declaration_var>SKColorBlue</declaration_var>, <declaration_comment>/*! Blue color */</declaration_comment>
    <declaration_var>SKColorPurple</declaration_var>, <declaration_comment>/*! Purple color */</declaration_comment>
    <declaration_var>SKColorWhite</declaration_var>, <declaration_comment>/*! White color */</declaration_comment>
    <declaration_var>SKColorCyan</declaration_var> <declaration_comment>/*! Cyan color */</declaration_comment>
};  </declaration>
<desc><p/></desc>
<autorelated>
<relateduid>//xsdoc_ref/doc/title:tdef/SKColor</relateduid>
</autorelated>
</typedef><typedef id="//xsdoc_ref/doc/title:tdef/SKColor" lang="c" type="funcPtr"><name>SKColor</name>
<abstract><p>Shell color type
</p></abstract>
<parameterlist>
<parameter><name>SKColorNone</name><desc><p>No color (clear)</p></desc></parameter>
<parameter><name>SKColorBlack</name><desc><p>Black color</p></desc></parameter>
<parameter><name>SKColorRed</name><desc><p>Red color</p></desc></parameter>
<parameter><name>SKColorGreen</name><desc><p>Green color</p></desc></parameter>
<parameter><name>SKColorYellow</name><desc><p>Yellow color</p></desc></parameter>
<parameter><name>SKColorBlue</name><desc><p>Blue color</p></desc></parameter>
<parameter><name>SKColorPurple</name><desc><p>Purple color</p></desc></parameter>
<parameter><name>SKColorWhite</name><desc><p>White color</p></desc></parameter>
<parameter><name>SKColorCyan</name><desc><p>Cyan color</p></desc></parameter>
</parameterlist>
<parsedparameterlist>
<parsedparameter><type></type><name>NSInteger</name></parsedparameter>
<parsedparameter><type></type><name>SKColor</name></parsedparameter>
<parsedparameter><type>SKColorNone,
          SKColorBlack,
         SKColorRed,
           SKColorGreen,
         SKColorYellow,
        SKColorBlue,
          SKColorPurple,
        SKColorWhite,
          SKColorCyan</type><name>SKColorPurple</name></parsedparameter>
<parsedparameter><type>SKColorNone,
          SKColorBlack,
         SKColorRed,
           SKColorGreen,
         SKColorYellow,
        SKColorBlue,
          SKColorPurple,
        SKColorWhite,
          SKColorCyan</type><name>SKColorBlack</name></parsedparameter>
<parsedparameter><type>SKColorNone,
          SKColorBlack,
         SKColorRed,
           SKColorGreen,
         SKColorYellow,
        SKColorBlue,
          SKColorPurple,
        SKColorWhite,
          SKColorCyan</type><name>SKColorGreen</name></parsedparameter>
<parsedparameter><type>SKColorNone,
          SKColorBlack,
         SKColorRed,
           SKColorGreen,
         SKColorYellow,
        SKColorBlue,
          SKColorPurple,
        SKColorWhite,
          SKColorCyan</type><name>SKColorRed</name></parsedparameter>
<parsedparameter><type>SKColorNone,
          SKColorBlack,
         SKColorRed,
           SKColorGreen,
         SKColorYellow,
        SKColorBlue,
          SKColorPurple,
        SKColorWhite,
          SKColorCyan</type><name>SKColorYellow</name></parsedparameter>
<parsedparameter><type>SKColorNone,
          SKColorBlack,
         SKColorRed,
           SKColorGreen,
         SKColorYellow,
        SKColorBlue,
          SKColorPurple,
        SKColorWhite,
          SKColorCyan</type><name>SKColorWhite</name></parsedparameter>
<parsedparameter><type>SKColorNone,
          SKColorBlack,
         SKColorRed,
           SKColorGreen,
         SKColorYellow,
        SKColorBlue,
          SKColorPurple,
        SKColorWhite,
          SKColorCyan</type><name>SKColorNone</name></parsedparameter>
<parsedparameter><type>SKColorNone,
          SKColorBlack,
         SKColorRed,
           SKColorGreen,
         SKColorYellow,
        SKColorBlue,
          SKColorPurple,
        SKColorWhite,
          SKColorCyan</type><name>SKColorBlue</name></parsedparameter>
<parsedparameter><type>SKColorNone,
          SKColorBlack,
         SKColorRed,
           SKColorGreen,
         SKColorYellow,
        SKColorBlue,
          SKColorPurple,
        SKColorWhite,
          SKColorCyan</type><name>SKColorCyan</name></parsedparameter>
</parsedparameterlist>
<attributelists><listattribute><name>See Also</name><list>
<item><name>NS_ENUM</name><value><hd_link logicalPath="//xsdoc_ref/c/tdef/NS_ENUM_DONTLINK_0" isseealso="yes">NS_ENUM</hd_link></value></item></list></listattribute>
</attributelists>
<declaration><declaration_keyword>typedef</declaration_keyword> <declaration_function>NS_ENUM</declaration_function>( <declaration_var>NSInteger</declaration_var>, <declaration_var>SKColor</declaration_var> ) { 
    <declaration_var>SKColorNone</declaration_var>, <declaration_comment>/*! No color (clear) */</declaration_comment>
    <declaration_var>SKColorBlack</declaration_var>, <declaration_comment>/*! Black color */</declaration_comment>
    <declaration_var>SKColorRed</declaration_var>, <declaration_comment>/*! Red color */</declaration_comment>
    <declaration_var>SKColorGreen</declaration_var>, <declaration_comment>/*! Green color */</declaration_comment>
    <declaration_var>SKColorYellow</declaration_var>, <declaration_comment>/*! Yellow color */</declaration_comment>
    <declaration_var>SKColorBlue</declaration_var>, <declaration_comment>/*! Blue color */</declaration_comment>
    <declaration_var>SKColorPurple</declaration_var>, <declaration_comment>/*! Purple color */</declaration_comment>
    <declaration_var>SKColorWhite</declaration_var>, <declaration_comment>/*! White color */</declaration_comment>
    <declaration_var>SKColorCyan</declaration_var> <declaration_comment>/*! Cyan color */</declaration_comment>
};  </declaration>
<desc><p/></desc>
<autorelated>
<relateduid>//xsdoc_ref/c/tdef/NS_ENUM_DONTLINK_0</relateduid>
</autorelated>
</typedef><typedef id="//xsdoc_ref/doc/title:tdef/SKStatus" lang="c" type="funcPtr"><name>SKStatus</name>
<abstract><p>Defines status icons
</p></abstract>
<parameterlist>
<parameter><name>SKStatusNone</name><desc><p>No status</p></desc></parameter>
<parameter><name>SKStatusSuccess</name><desc><p>Sucess status icon</p></desc></parameter>
<parameter><name>SKStatusFatal</name><desc><p>Fatal error status icon</p></desc></parameter>
<parameter><name>SKStatusError</name><desc><p>Error status icon</p></desc></parameter>
<parameter><name>SKStatusWarning</name><desc><p>Warning status icon</p></desc></parameter>
<parameter><name>SKStatusInfo</name><desc><p>Info status icon</p></desc></parameter>
<parameter><name>SKStatusDebug</name><desc><p>Debug status icon</p></desc></parameter>
<parameter><name>SKStatusBuild</name><desc><p>Build status icon</p></desc></parameter>
<parameter><name>SKStatusInstall</name><desc><p>Install status icon</p></desc></parameter>
<parameter><name>SKStatusIdea</name><desc><p>Idea status icon</p></desc></parameter>
<parameter><name>SKStatusSettings</name><desc><p>Settings status icon</p></desc></parameter>
<parameter><name>SKStatusSecurity</name><desc><p>Security status icon</p></desc></parameter>
<parameter><name>SKStatusExecute</name><desc><p>Executing status icon</p></desc></parameter>
<parameter><name>SKStatusSearch</name><desc><p>Search status icon</p></desc></parameter>
<parameter><name>SKStatusTarget</name><desc><p>Target status icon</p></desc></parameter>
<parameter><name>SKStatusComment</name><desc><p>Comment status icon</p></desc></parameter>
<parameter><name>SKStatusFile</name><desc><p>File status icon</p></desc></parameter>
<parameter><name>SKStatusFolder</name><desc><p>Folder status icon</p></desc></parameter>
<parameter><name>SKStatusTrash</name><desc><p>Trash status icon</p></desc></parameter>
<parameter><name>SKStatusLink</name><desc><p>Link status icon</p></desc></parameter>
<parameter><name>SKStatusMail</name><desc><p>Mail message status icon</p></desc></parameter>
<parameter><name>SKStatusAttachement</name><desc><p>Message attachmnet status icon</p></desc></parameter>
<parameter><name>SKStatusEdit</name><desc><p>Edit status icon</p></desc></parameter>
<parameter><name>SKStatusPin</name><desc><p>Push pin status icon</p></desc></parameter>
<parameter><name>SKStatusLock</name><desc><p>Lock status icon</p></desc></parameter>
<parameter><name>SKStatusRocket</name><desc><p>Rocket status icon</p></desc></parameter>
<parameter><name>SKStatusFire</name><desc><p>Fire status icon</p></desc></parameter>
<parameter><name>SKStatusLightning</name><desc><p>Lightning status icon</p></desc></parameter>
<parameter><name>SKStatusBug</name><desc><p>Bug status icon</p></desc></parameter>
</parameterlist>
<parsedparameterlist>
<parsedparameter><type></type><name>NSInteger</name></parsedparameter>
<parsedparameter><type></type><name>SKStatus</name></parsedparameter>
<parsedparameter><type>SKStatusNone,
                 SKStatusSuccess,
              SKStatusFatal,
                SKStatusError,
                SKStatusWarning,
              SKStatusInfo,
                 SKStatusDebug,
                SKStatusBuild,
                SKStatusInstall,
              SKStatusIdea,
                 SKStatusSettings,
             SKStatusSecurity,
             SKStatusExecute,
              SKStatusSearch,
               SKStatusTarget,
               SKStatusComment,
              SKStatusFile,
                 SKStatusFolder,
               SKStatusTrash,
                SKStatusLink,
                 SKStatusMail,
                 SKStatusAttachement,
          SKStatusEdit,
                 SKStatusPin,
                  SKStatusLock,
                 SKStatusRocket,
               SKStatusFire,
                 SKStatusLightning,
             SKStatusBug</type><name>SKStatusAttachement</name></parsedparameter>
<parsedparameter><type>SKStatusNone,
                 SKStatusSuccess,
              SKStatusFatal,
                SKStatusError,
                SKStatusWarning,
              SKStatusInfo,
                 SKStatusDebug,
                SKStatusBuild,
                SKStatusInstall,
              SKStatusIdea,
                 SKStatusSettings,
             SKStatusSecurity,
             SKStatusExecute,
              SKStatusSearch,
               SKStatusTarget,
               SKStatusComment,
              SKStatusFile,
                 SKStatusFolder,
               SKStatusTrash,
                SKStatusLink,
                 SKStatusMail,
                 SKStatusAttachement,
          SKStatusEdit,
                 SKStatusPin,
                  SKStatusLock,
                 SKStatusRocket,
               SKStatusFire,
                 SKStatusLightning,
             SKStatusBug</type><name>SKStatusSettings</name></parsedparameter>
<parsedparameter><type>SKStatusNone,
                 SKStatusSuccess,
              SKStatusFatal,
                SKStatusError,
                SKStatusWarning,
              SKStatusInfo,
                 SKStatusDebug,
                SKStatusBuild,
                SKStatusInstall,
              SKStatusIdea,
                 SKStatusSettings,
             SKStatusSecurity,
             SKStatusExecute,
              SKStatusSearch,
               SKStatusTarget,
               SKStatusComment,
              SKStatusFile,
                 SKStatusFolder,
               SKStatusTrash,
                SKStatusLink,
                 SKStatusMail,
                 SKStatusAttachement,
          SKStatusEdit,
                 SKStatusPin,
                  SKStatusLock,
                 SKStatusRocket,
               SKStatusFire,
                 SKStatusLightning,
             SKStatusBug</type><name>SKStatusNone</name></parsedparameter>
<parsedparameter><type>SKStatusNone,
                 SKStatusSuccess,
              SKStatusFatal,
                SKStatusError,
                SKStatusWarning,
              SKStatusInfo,
                 SKStatusDebug,
                SKStatusBuild,
                SKStatusInstall,
              SKStatusIdea,
                 SKStatusSettings,
             SKStatusSecurity,
             SKStatusExecute,
              SKStatusSearch,
               SKStatusTarget,
               SKStatusComment,
              SKStatusFile,
                 SKStatusFolder,
               SKStatusTrash,
                SKStatusLink,
                 SKStatusMail,
                 SKStatusAttachement,
          SKStatusEdit,
                 SKStatusPin,
                  SKStatusLock,
                 SKStatusRocket,
               SKStatusFire,
                 SKStatusLightning,
             SKStatusBug</type><name>SKStatusLock</name></parsedparameter>
<parsedparameter><type>SKStatusNone,
                 SKStatusSuccess,
              SKStatusFatal,
                SKStatusError,
                SKStatusWarning,
              SKStatusInfo,
                 SKStatusDebug,
                SKStatusBuild,
                SKStatusInstall,
              SKStatusIdea,
                 SKStatusSettings,
             SKStatusSecurity,
             SKStatusExecute,
              SKStatusSearch,
               SKStatusTarget,
               SKStatusComment,
              SKStatusFile,
                 SKStatusFolder,
               SKStatusTrash,
                SKStatusLink,
                 SKStatusMail,
                 SKStatusAttachement,
          SKStatusEdit,
                 SKStatusPin,
                  SKStatusLock,
                 SKStatusRocket,
               SKStatusFire,
                 SKStatusLightning,
             SKStatusBug</type><name>SKStatusFire</name></parsedparameter>
<parsedparameter><type>SKStatusNone,
                 SKStatusSuccess,
              SKStatusFatal,
                SKStatusError,
                SKStatusWarning,
              SKStatusInfo,
                 SKStatusDebug,
                SKStatusBuild,
                SKStatusInstall,
              SKStatusIdea,
                 SKStatusSettings,
             SKStatusSecurity,
             SKStatusExecute,
              SKStatusSearch,
               SKStatusTarget,
               SKStatusComment,
              SKStatusFile,
                 SKStatusFolder,
               SKStatusTrash,
                SKStatusLink,
                 SKStatusMail,
                 SKStatusAttachement,
          SKStatusEdit,
                 SKStatusPin,
                  SKStatusLock,
                 SKStatusRocket,
               SKStatusFire,
                 SKStatusLightning,
             SKStatusBug</type><name>SKStatusLink</name></parsedparameter>
<parsedparameter><type>SKStatusNone,
                 SKStatusSuccess,
              SKStatusFatal,
                SKStatusError,
                SKStatusWarning,
              SKStatusInfo,
                 SKStatusDebug,
                SKStatusBuild,
                SKStatusInstall,
              SKStatusIdea,
                 SKStatusSettings,
             SKStatusSecurity,
             SKStatusExecute,
              SKStatusSearch,
               SKStatusTarget,
               SKStatusComment,
              SKStatusFile,
                 SKStatusFolder,
               SKStatusTrash,
                SKStatusLink,
                 SKStatusMail,
                 SKStatusAttachement,
          SKStatusEdit,
                 SKStatusPin,
                  SKStatusLock,
                 SKStatusRocket,
               SKStatusFire,
                 SKStatusLightning,
             SKStatusBug</type><name>SKStatusFile</name></parsedparameter>
<parsedparameter><type>SKStatusNone,
                 SKStatusSuccess,
              SKStatusFatal,
                SKStatusError,
                SKStatusWarning,
              SKStatusInfo,
                 SKStatusDebug,
                SKStatusBuild,
                SKStatusInstall,
              SKStatusIdea,
                 SKStatusSettings,
             SKStatusSecurity,
             SKStatusExecute,
              SKStatusSearch,
               SKStatusTarget,
               SKStatusComment,
              SKStatusFile,
                 SKStatusFolder,
               SKStatusTrash,
                SKStatusLink,
                 SKStatusMail,
                 SKStatusAttachement,
          SKStatusEdit,
                 SKStatusPin,
                  SKStatusLock,
                 SKStatusRocket,
               SKStatusFire,
                 SKStatusLightning,
             SKStatusBug</type><name>SKStatusSuccess</name></parsedparameter>
<parsedparameter><type>SKStatusNone,
                 SKStatusSuccess,
              SKStatusFatal,
                SKStatusError,
                SKStatusWarning,
              SKStatusInfo,
                 SKStatusDebug,
                SKStatusBuild,
                SKStatusInstall,
              SKStatusIdea,
                 SKStatusSettings,
             SKStatusSecurity,
             SKStatusExecute,
              SKStatusSearch,
               SKStatusTarget,
               SKStatusComment,
              SKStatusFile,
                 SKStatusFolder,
               SKStatusTrash,
                SKStatusLink,
                 SKStatusMail,
                 SKStatusAttachement,
          SKStatusEdit,
                 SKStatusPin,
                  SKStatusLock,
                 SKStatusRocket,
               SKStatusFire,
                 SKStatusLightning,
             SKStatusBug</type><name>SKStatusTarget</name></parsedparameter>
<parsedparameter><type>SKStatusNone,
                 SKStatusSuccess,
              SKStatusFatal,
                SKStatusError,
                SKStatusWarning,
              SKStatusInfo,
                 SKStatusDebug,
                SKStatusBuild,
                SKStatusInstall,
              SKStatusIdea,
                 SKStatusSettings,
             SKStatusSecurity,
             SKStatusExecute,
              SKStatusSearch,
               SKStatusTarget,
               SKStatusComment,
              SKStatusFile,
                 SKStatusFolder,
               SKStatusTrash,
                SKStatusLink,
                 SKStatusMail,
                 SKStatusAttachement,
          SKStatusEdit,
                 SKStatusPin,
                  SKStatusLock,
                 SKStatusRocket,
               SKStatusFire,
                 SKStatusLightning,
             SKStatusBug</type><name>SKStatusExecute</name></parsedparameter>
<parsedparameter><type>SKStatusNone,
                 SKStatusSuccess,
              SKStatusFatal,
                SKStatusError,
                SKStatusWarning,
              SKStatusInfo,
                 SKStatusDebug,
                SKStatusBuild,
                SKStatusInstall,
              SKStatusIdea,
                 SKStatusSettings,
             SKStatusSecurity,
             SKStatusExecute,
              SKStatusSearch,
               SKStatusTarget,
               SKStatusComment,
              SKStatusFile,
                 SKStatusFolder,
               SKStatusTrash,
                SKStatusLink,
                 SKStatusMail,
                 SKStatusAttachement,
          SKStatusEdit,
                 SKStatusPin,
                  SKStatusLock,
                 SKStatusRocket,
               SKStatusFire,
                 SKStatusLightning,
             SKStatusBug</type><name>SKStatusPin</name></parsedparameter>
<parsedparameter><type>SKStatusNone,
                 SKStatusSuccess,
              SKStatusFatal,
                SKStatusError,
                SKStatusWarning,
              SKStatusInfo,
                 SKStatusDebug,
                SKStatusBuild,
                SKStatusInstall,
              SKStatusIdea,
                 SKStatusSettings,
             SKStatusSecurity,
             SKStatusExecute,
              SKStatusSearch,
               SKStatusTarget,
               SKStatusComment,
              SKStatusFile,
                 SKStatusFolder,
               SKStatusTrash,
                SKStatusLink,
                 SKStatusMail,
                 SKStatusAttachement,
          SKStatusEdit,
                 SKStatusPin,
                  SKStatusLock,
                 SKStatusRocket,
               SKStatusFire,
                 SKStatusLightning,
             SKStatusBug</type><name>SKStatusInfo</name></parsedparameter>
<parsedparameter><type>SKStatusNone,
                 SKStatusSuccess,
              SKStatusFatal,
                SKStatusError,
                SKStatusWarning,
              SKStatusInfo,
                 SKStatusDebug,
                SKStatusBuild,
                SKStatusInstall,
              SKStatusIdea,
                 SKStatusSettings,
             SKStatusSecurity,
             SKStatusExecute,
              SKStatusSearch,
               SKStatusTarget,
               SKStatusComment,
              SKStatusFile,
                 SKStatusFolder,
               SKStatusTrash,
                SKStatusLink,
                 SKStatusMail,
                 SKStatusAttachement,
          SKStatusEdit,
                 SKStatusPin,
                  SKStatusLock,
                 SKStatusRocket,
               SKStatusFire,
                 SKStatusLightning,
             SKStatusBug</type><name>SKStatusWarning</name></parsedparameter>
<parsedparameter><type>SKStatusNone,
                 SKStatusSuccess,
              SKStatusFatal,
                SKStatusError,
                SKStatusWarning,
              SKStatusInfo,
                 SKStatusDebug,
                SKStatusBuild,
                SKStatusInstall,
              SKStatusIdea,
                 SKStatusSettings,
             SKStatusSecurity,
             SKStatusExecute,
              SKStatusSearch,
               SKStatusTarget,
               SKStatusComment,
              SKStatusFile,
                 SKStatusFolder,
               SKStatusTrash,
                SKStatusLink,
                 SKStatusMail,
                 SKStatusAttachement,
          SKStatusEdit,
                 SKStatusPin,
                  SKStatusLock,
                 SKStatusRocket,
               SKStatusFire,
                 SKStatusLightning,
             SKStatusBug</type><name>SKStatusIdea</name></parsedparameter>
<parsedparameter><type>SKStatusNone,
                 SKStatusSuccess,
              SKStatusFatal,
                SKStatusError,
                SKStatusWarning,
              SKStatusInfo,
                 SKStatusDebug,
                SKStatusBuild,
                SKStatusInstall,
              SKStatusIdea,
                 SKStatusSettings,
             SKStatusSecurity,
             SKStatusExecute,
              SKStatusSearch,
               SKStatusTarget,
               SKStatusComment,
              SKStatusFile,
                 SKStatusFolder,
               SKStatusTrash,
                SKStatusLink,
                 SKStatusMail,
                 SKStatusAttachement,
          SKStatusEdit,
                 SKStatusPin,
                  SKStatusLock,
                 SKStatusRocket,
               SKStatusFire,
                 SKStatusLightning,
             SKStatusBug</type><name>SKStatusLightning</name></parsedparameter>
<parsedparameter><type>SKStatusNone,
                 SKStatusSuccess,
              SKStatusFatal,
                SKStatusError,
                SKStatusWarning,
              SKStatusInfo,
                 SKStatusDebug,
                SKStatusBuild,
                SKStatusInstall,
              SKStatusIdea,
                 SKStatusSettings,
             SKStatusSecurity,
             SKStatusExecute,
              SKStatusSearch,
               SKStatusTarget,
               SKStatusComment,
              SKStatusFile,
                 SKStatusFolder,
               SKStatusTrash,
                SKStatusLink,
                 SKStatusMail,
                 SKStatusAttachement,
          SKStatusEdit,
                 SKStatusPin,
                  SKStatusLock,
                 SKStatusRocket,
               SKStatusFire,
                 SKStatusLightning,
             SKStatusBug</type><name>SKStatusTrash</name></parsedparameter>
<parsedparameter><type>SKStatusNone,
                 SKStatusSuccess,
              SKStatusFatal,
                SKStatusError,
                SKStatusWarning,
              SKStatusInfo,
                 SKStatusDebug,
                SKStatusBuild,
                SKStatusInstall,
              SKStatusIdea,
                 SKStatusSettings,
             SKStatusSecurity,
             SKStatusExecute,
              SKStatusSearch,
               SKStatusTarget,
               SKStatusComment,
              SKStatusFile,
                 SKStatusFolder,
               SKStatusTrash,
                SKStatusLink,
                 SKStatusMail,
                 SKStatusAttachement,
          SKStatusEdit,
                 SKStatusPin,
                  SKStatusLock,
                 SKStatusRocket,
               SKStatusFire,
                 SKStatusLightning,
             SKStatusBug</type><name>SKStatusInstall</name></parsedparameter>
<parsedparameter><type>SKStatusNone,
                 SKStatusSuccess,
              SKStatusFatal,
                SKStatusError,
                SKStatusWarning,
              SKStatusInfo,
                 SKStatusDebug,
                SKStatusBuild,
                SKStatusInstall,
              SKStatusIdea,
                 SKStatusSettings,
             SKStatusSecurity,
             SKStatusExecute,
              SKStatusSearch,
               SKStatusTarget,
               SKStatusComment,
              SKStatusFile,
                 SKStatusFolder,
               SKStatusTrash,
                SKStatusLink,
                 SKStatusMail,
                 SKStatusAttachement,
          SKStatusEdit,
                 SKStatusPin,
                  SKStatusLock,
                 SKStatusRocket,
               SKStatusFire,
                 SKStatusLightning,
             SKStatusBug</type><name>SKStatusMail</name></parsedparameter>
<parsedparameter><type>SKStatusNone,
                 SKStatusSuccess,
              SKStatusFatal,
                SKStatusError,
                SKStatusWarning,
              SKStatusInfo,
                 SKStatusDebug,
                SKStatusBuild,
                SKStatusInstall,
              SKStatusIdea,
                 SKStatusSettings,
             SKStatusSecurity,
             SKStatusExecute,
              SKStatusSearch,
               SKStatusTarget,
               SKStatusComment,
              SKStatusFile,
                 SKStatusFolder,
               SKStatusTrash,
                SKStatusLink,
                 SKStatusMail,
                 SKStatusAttachement,
          SKStatusEdit,
                 SKStatusPin,
                  SKStatusLock,
                 SKStatusRocket,
               SKStatusFire,
                 SKStatusLightning,
             SKStatusBug</type><name>SKStatusSecurity</name></parsedparameter>
<parsedparameter><type>SKStatusNone,
                 SKStatusSuccess,
              SKStatusFatal,
                SKStatusError,
                SKStatusWarning,
              SKStatusInfo,
                 SKStatusDebug,
                SKStatusBuild,
                SKStatusInstall,
              SKStatusIdea,
                 SKStatusSettings,
             SKStatusSecurity,
             SKStatusExecute,
              SKStatusSearch,
               SKStatusTarget,
               SKStatusComment,
              SKStatusFile,
                 SKStatusFolder,
               SKStatusTrash,
                SKStatusLink,
                 SKStatusMail,
                 SKStatusAttachement,
          SKStatusEdit,
                 SKStatusPin,
                  SKStatusLock,
                 SKStatusRocket,
               SKStatusFire,
                 SKStatusLightning,
             SKStatusBug</type><name>SKStatusEdit</name></parsedparameter>
<parsedparameter><type>SKStatusNone,
                 SKStatusSuccess,
              SKStatusFatal,
                SKStatusError,
                SKStatusWarning,
              SKStatusInfo,
                 SKStatusDebug,
                SKStatusBuild,
                SKStatusInstall,
              SKStatusIdea,
                 SKStatusSettings,
             SKStatusSecurity,
             SKStatusExecute,
              SKStatusSearch,
               SKStatusTarget,
               SKStatusComment,
              SKStatusFile,
                 SKStatusFolder,
               SKStatusTrash,
                SKStatusLink,
                 SKStatusMail,
                 SKStatusAttachement,
          SKStatusEdit,
                 SKStatusPin,
                  SKStatusLock,
                 SKStatusRocket,
               SKStatusFire,
                 SKStatusLightning,
             SKStatusBug</type><name>SKStatusDebug</name></parsedparameter>
<parsedparameter><type>SKStatusNone,
                 SKStatusSuccess,
              SKStatusFatal,
                SKStatusError,
                SKStatusWarning,
              SKStatusInfo,
                 SKStatusDebug,
                SKStatusBuild,
                SKStatusInstall,
              SKStatusIdea,
                 SKStatusSettings,
             SKStatusSecurity,
             SKStatusExecute,
              SKStatusSearch,
               SKStatusTarget,
               SKStatusComment,
              SKStatusFile,
                 SKStatusFolder,
               SKStatusTrash,
                SKStatusLink,
                 SKStatusMail,
                 SKStatusAttachement,
          SKStatusEdit,
                 SKStatusPin,
                  SKStatusLock,
                 SKStatusRocket,
               SKStatusFire,
                 SKStatusLightning,
             SKStatusBug</type><name>SKStatusSearch</name></parsedparameter>
<parsedparameter><type>SKStatusNone,
                 SKStatusSuccess,
              SKStatusFatal,
                SKStatusError,
                SKStatusWarning,
              SKStatusInfo,
                 SKStatusDebug,
                SKStatusBuild,
                SKStatusInstall,
              SKStatusIdea,
                 SKStatusSettings,
             SKStatusSecurity,
             SKStatusExecute,
              SKStatusSearch,
               SKStatusTarget,
               SKStatusComment,
              SKStatusFile,
                 SKStatusFolder,
               SKStatusTrash,
                SKStatusLink,
                 SKStatusMail,
                 SKStatusAttachement,
          SKStatusEdit,
                 SKStatusPin,
                  SKStatusLock,
                 SKStatusRocket,
               SKStatusFire,
                 SKStatusLightning,
             SKStatusBug</type><name>SKStatusFolder</name></parsedparameter>
<parsedparameter><type>SKStatusNone,
                 SKStatusSuccess,
              SKStatusFatal,
                SKStatusError,
                SKStatusWarning,
              SKStatusInfo,
                 SKStatusDebug,
                SKStatusBuild,
                SKStatusInstall,
              SKStatusIdea,
                 SKStatusSettings,
             SKStatusSecurity,
             SKStatusExecute,
              SKStatusSearch,
               SKStatusTarget,
               SKStatusComment,
              SKStatusFile,
                 SKStatusFolder,
               SKStatusTrash,
                SKStatusLink,
                 SKStatusMail,
                 SKStatusAttachement,
          SKStatusEdit,
                 SKStatusPin,
                  SKStatusLock,
                 SKStatusRocket,
               SKStatusFire,
                 SKStatusLightning,
             SKStatusBug</type><name>SKStatusBuild</name></parsedparameter>
<parsedparameter><type>SKStatusNone,
                 SKStatusSuccess,
              SKStatusFatal,
                SKStatusError,
                SKStatusWarning,
              SKStatusInfo,
                 SKStatusDebug,
                SKStatusBuild,
                SKStatusInstall,
              SKStatusIdea,
                 SKStatusSettings,
             SKStatusSecurity,
             SKStatusExecute,
              SKStatusSearch,
               SKStatusTarget,
               SKStatusComment,
              SKStatusFile,
                 SKStatusFolder,
               SKStatusTrash,
                SKStatusLink,
                 SKStatusMail,
                 SKStatusAttachement,
          SKStatusEdit,
                 SKStatusPin,
                  SKStatusLock,
                 SKStatusRocket,
               SKStatusFire,
                 SKStatusLightning,
             SKStatusBug</type><name>SKStatusError</name></parsedparameter>
<parsedparameter><type>SKStatusNone,
                 SKStatusSuccess,
              SKStatusFatal,
                SKStatusError,
                SKStatusWarning,
              SKStatusInfo,
                 SKStatusDebug,
                SKStatusBuild,
                SKStatusInstall,
              SKStatusIdea,
                 SKStatusSettings,
             SKStatusSecurity,
             SKStatusExecute,
              SKStatusSearch,
               SKStatusTarget,
               SKStatusComment,
              SKStatusFile,
                 SKStatusFolder,
               SKStatusTrash,
                SKStatusLink,
                 SKStatusMail,
                 SKStatusAttachement,
          SKStatusEdit,
                 SKStatusPin,
                  SKStatusLock,
                 SKStatusRocket,
               SKStatusFire,
                 SKStatusLightning,
             SKStatusBug</type><name>SKStatusComment</name></parsedparameter>
<parsedparameter><type>SKStatusNone,
                 SKStatusSuccess,
              SKStatusFatal,
                SKStatusError,
                SKStatusWarning,
              SKStatusInfo,
                 SKStatusDebug,
                SKStatusBuild,
                SKStatusInstall,
              SKStatusIdea,
                 SKStatusSettings,
             SKStatusSecurity,
             SKStatusExecute,
              SKStatusSearch,
               SKStatusTarget,
               SKStatusComment,
              SKStatusFile,
                 SKStatusFolder,
               SKStatusTrash,
                SKStatusLink,
                 SKStatusMail,
                 SKStatusAttachement,
          SKStatusEdit,
                 SKStatusPin,
                  SKStatusLock,
                 SKStatusRocket,
               SKStatusFire,
                 SKStatusLightning,
             SKStatusBug</type><name>SKStatusFatal</name></parsedparameter>
<parsedparameter><type>SKStatusNone,
                 SKStatusSuccess,
              SKStatusFatal,
                SKStatusError,
                SKStatusWarning,
              SKStatusInfo,
                 SKStatusDebug,
                SKStatusBuild,
                SKStatusInstall,
              SKStatusIdea,
                 SKStatusSettings,
             SKStatusSecurity,
             SKStatusExecute,
              SKStatusSearch,
               SKStatusTarget,
               SKStatusComment,
              SKStatusFile,
                 SKStatusFolder,
               SKStatusTrash,
                SKStatusLink,
                 SKStatusMail,
                 SKStatusAttachement,
          SKStatusEdit,
                 SKStatusPin,
                  SKStatusLock,
                 SKStatusRocket,
               SKStatusFire,
                 SKStatusLightning,
             SKStatusBug</type><name>SKStatusRocket</name></parsedparameter>
<parsedparameter><type>SKStatusNone,
                 SKStatusSuccess,
              SKStatusFatal,
                SKStatusError,
                SKStatusWarning,
              SKStatusInfo,
                 SKStatusDebug,
                SKStatusBuild,
                SKStatusInstall,
              SKStatusIdea,
                 SKStatusSettings,
             SKStatusSecurity,
             SKStatusExecute,
              SKStatusSearch,
               SKStatusTarget,
               SKStatusComment,
              SKStatusFile,
                 SKStatusFolder,
               SKStatusTrash,
                SKStatusLink,
                 SKStatusMail,
                 SKStatusAttachement,
          SKStatusEdit,
                 SKStatusPin,
                  SKStatusLock,
                 SKStatusRocket,
               SKStatusFire,
                 SKStatusLightning,
             SKStatusBug</type><name>SKStatusBug</name></parsedparameter>
</parsedparameterlist>
<attributelists><listattribute><name>See Also</name><list>
<item><name>NS_ENUM</name><value><hd_link logicalPath="//xsdoc_ref/c/tdef/NS_ENUM" isseealso="yes">NS_ENUM</hd_link></value></item></list></listattribute>
</attributelists>
<declaration><declaration_keyword>typedef</declaration_keyword> <declaration_function>NS_ENUM</declaration_function>( <declaration_var>NSInteger</declaration_var>, <declaration_var>SKStatus</declaration_var> ) { 
    <declaration_var>SKStatusNone</declaration_var>, <declaration_comment>/*! No status */</declaration_comment>
    <declaration_var>SKStatusSuccess</declaration_var>, <declaration_comment>/*! Sucess status icon */</declaration_comment>
    <declaration_var>SKStatusFatal</declaration_var>, <declaration_comment>/*! Fatal error status icon */</declaration_comment>
    <declaration_var>SKStatusError</declaration_var>, <declaration_comment>/*! Error status icon */</declaration_comment>
    <declaration_var>SKStatusWarning</declaration_var>, <declaration_comment>/*! Warning status icon */</declaration_comment>
    <declaration_var>SKStatusInfo</declaration_var>, <declaration_comment>/*! Info status icon */</declaration_comment>
    <declaration_var>SKStatusDebug</declaration_var>, <declaration_comment>/*! Debug status icon */</declaration_comment>
    <declaration_var>SKStatusBuild</declaration_var>, <declaration_comment>/*! Build status icon */</declaration_comment>
    <declaration_var>SKStatusInstall</declaration_var>, <declaration_comment>/*! Install status icon */</declaration_comment>
    <declaration_var>SKStatusIdea</declaration_var>, <declaration_comment>/*! Idea status icon */</declaration_comment>
    <declaration_var>SKStatusSettings</declaration_var>, <declaration_comment>/*! Settings status icon */</declaration_comment>
    <declaration_var>SKStatusSecurity</declaration_var>, <declaration_comment>/*! Security status icon */</declaration_comment>
    <declaration_var>SKStatusExecute</declaration_var>, <declaration_comment>/*! Executing status icon */</declaration_comment>
    <declaration_var>SKStatusSearch</declaration_var>, <declaration_comment>/*! Search status icon */</declaration_comment>
    <declaration_var>SKStatusTarget</declaration_var>, <declaration_comment>/*! Target status icon */</declaration_comment>
    <declaration_var>SKStatusComment</declaration_var>, <declaration_comment>/*! Comment status icon */</declaration_comment>
    <declaration_var>SKStatusFile</declaration_var>, <declaration_comment>/*! File status icon */</declaration_comment>
    <declaration_var>SKStatusFolder</declaration_var>, <declaration_comment>/*! Folder status icon */</declaration_comment>
    <declaration_var>SKStatusTrash</declaration_var>, <declaration_comment>/*! Trash status icon */</declaration_comment>
    <declaration_var>SKStatusLink</declaration_var>, <declaration_comment>/*! Link status icon */</declaration_comment>
    <declaration_var>SKStatusMail</declaration_var>, <declaration_comment>/*! Mail message status icon */</declaration_comment>
    <declaration_var>SKStatusAttachement</declaration_var>, <declaration_comment>/*! Message attachmnet status icon */</declaration_comment>
    <declaration_var>SKStatusEdit</declaration_var>, <declaration_comment>/*! Edit status icon */</declaration_comment>
    <declaration_var>SKStatusPin</declaration_var>, <declaration_comment>/*! Push pin status icon */</declaration_comment>
    <declaration_var>SKStatusLock</declaration_var>, <declaration_comment>/*! Lock status icon */</declaration_comment>
    <declaration_var>SKStatusRocket</declaration_var>, <declaration_comment>/*! Rocket status icon */</declaration_comment>
    <declaration_var>SKStatusFire</declaration_var>, <declaration_comment>/*! Fire status icon */</declaration_comment>
    <declaration_var>SKStatusLightning</declaration_var>, <declaration_comment>/*! Lightning status icon */</declaration_comment>
    <declaration_var>SKStatusBug</declaration_var> <declaration_comment>/*! Bug status icon */</declaration_comment>
};  </declaration>
<desc><p/></desc>
<autorelated>
<relateduid>//xsdoc_ref/c/tdef/NS_ENUM</relateduid>
</autorelated>
</typedef></typedefs><copyrightinfo>&#169; (c) 2017, Jean-David Gadina - www.xs-labs.com
</copyrightinfo>
<timestamp>Monday, May 15, 2017</timestamp>
</header>